AUTHORS.rst
CONTRIBUTING.rst
HISTORY.rst
LICENSE
MANIFEST.in
README.rst
setup.cfg
setup.py
calculatortc2/__init__.py
calculatortc2/calculatortc2.py
calculatortc2/cli.py
calculatortc2.egg-info/PKG-INFO
calculatortc2.egg-info/SOURCES.txt
calculatortc2.egg-info/dependency_links.txt
calculatortc2.egg-info/entry_points.txt
calculatortc2.egg-info/not-zip-safe
calculatortc2.egg-info/requires.txt
calculatortc2.egg-info/top_level.txt
docs/Makefile
docs/authors.rst
docs/conf.py
docs/contributing.rst
docs/history.rst
docs/index.rst
docs/installation.rst
docs/make.bat
docs/readme.rst
docs/usage.rst
tests/__init__.py
tests/test_calculatortc2.py